llmserver/__init__.py
pyllmserver-0.0.1.dist-info/LICENSE
pyllmserver-0.0.1.dist-info/WHEEL
pyllmserver-0.0.1.dist-info/METADATA
pyllmserver-0.0.1.dist-info/RECORD
